psql_cmd_hook/__init__.py
psql_cmd_hook/psql_cmd_hook.py
amsterdam_airflow_psql_cmd_hook-1.1.dist-info/WHEEL
amsterdam_airflow_psql_cmd_hook-1.1.dist-info/METADATA
amsterdam_airflow_psql_cmd_hook-1.1.dist-info/RECORD
